requirements.txt
setup.py
true_case_path/__init__.py
true_case_path.egg-info/PKG-INFO
true_case_path.egg-info/SOURCES.txt
true_case_path.egg-info/dependency_links.txt
true_case_path.egg-info/top_level.txt