Metadata-Version: 2.1
Name: true-case-path
Version: 2020.7.1
Summary: get case exact path as stored in the filesystem
Home-page: https://github.com/andrewp-as-is/true-case-path.py
License: Unlicense
Keywords: case path
Platform: UNKNOWN
Classifier: License :: Public Domain
Classifier: Operating System :: OS Independent
Classifier: Programming Language :: Python :: 3
